Workbook

Sheet CorST
A1: Слово | B1: Частота-CorST | C1: IPM-CorST | D1: Ранг-CorST | E1: Номер строки, на которой слово стоит в RLC | F1: IPM-RLC
A2: в | B2: 35889 | C2: 11520.564 | D2: =RANK(B2,$B:$B,0) -> 1 | E2: =MATCH(A2,RLC!$A:$A,0) -> 3 | F2: {=INDEX(RLC!$C:$C,E2)} -> 37993.234
A3: и | B3: 31435 | C3: 10090.806 | D3: =RANK(B3,$B:$B,0) -> 2 | E3: =MATCH(A3,RLC!$A:$A,0) -> 2 | F3: {=INDEX(RLC!$C:$C,E3)} -> 38334.702
A4: на | B4: 13212 | C4: 4241.1239 | D4: =RANK(B4,$B:$B,0) -> 3 | E4: =MATCH(A4,RLC!$A:$A,0) -> 5 | F4: {=INDEX(RLC!$C:$C,E4)} -> 13265.412
A5: не | B5: 11811 | C5: 3791.3953 | D5: =RANK(B5,$B:$B,0) -> 4 | E5: =MATCH(A5,RLC!$A:$A,0) -> 6 | F5: {=INDEX(RLC!$C:$C,E5)} -> 12860.168
A6: с | B6: 11363 | C6: 3647.5848 | D6: =RANK(B6,$B:$B,0) -> 5 | E6: =MATCH(A6,RLC!$A:$A,0) -> 8 | F6: {=INDEX(RLC!$C:$C,E6)} -> 9178.432
A7: что | B7: 10265 | C7: 3295.1208 | D7: =RANK(B7,$B:$B,0) -> 6 | E7: =MATCH(A7,RLC!$A:$A,0) -> 4 | F7: {=INDEX(RLC!$C:$C,E7)} -> 16305.402
A8: как | B8: 7396 | C8: 2374.1562 | D8: =RANK(B8,$B:$B,0) -> 7 | E8: =MATCH(A8,RLC!$A:$A,0) -> 9 | F8: {=INDEX(RLC!$C:$C,E8)} -> 8273.6097
A9: к | B9: 6790 | C9: 2179.6269 | D9: =RANK(B9,$B:$B,0) -> 8 | E9: =MATCH(A9,RLC!$A:$A,0) -> 15 | F9: {=INDEX(RLC!$C:$C,E9)} -> 4742.0127
A10: а | B10: 5924 | C10: 1901.6362 | D10: =RANK(B10,$B:$B,0) -> 9 | E10: =MATCH(A10,RLC!$A:$A,0) -> 20 | F10: {=INDEX(RLC!$C:$C,E10)} -> 3449.2197
A11: для | B11: 5652 | C11: 1814.3227 | D11: =RANK(B11,$B:$B,0) -> 10 | E11: =MATCH(A11,RLC!$A:$A,0) -> 14 | F11: {=INDEX(RLC!$C:$C,E11)} -> 5009.0748
A12: по | B12: 5634 | C12: 1808.5447 | D12: =RANK(B12,$B:$B,0) -> 11 | E12: =MATCH(A12,RLC!$A:$A,0) -> 16 | F12: {=INDEX(RLC!$C:$C,E12)} -> 4641.034
A13: о | B13: 4912 | C13: 1576.7787 | D13: =RANK(B13,$B:$B,0) -> 12 | E13: =MATCH(A13,RLC!$A:$A,0) -> 13 | F13: {=INDEX(RLC!$C:$C,E13)} -> 5022.3615
... A1349: форм | B1349: 92 | C1349: 29.532501 | D1349: =RANK(B1349,$B:$B,0) -> 1326 | E1349: =MATCH(A1349,RLC!$A:$A,0) -> 5289 | F1349: {=INDEX(RLC!$C:$C,E1349)} -> 21.258673
A1350: школе | B1350: 92 | C1350: 29.532501 | D1350: =RANK(B1350,$B:$B,0) -> 1326 | E1350: =MATCH(A1350,RLC!$A:$A,0) -> 404 | F1350: {=INDEX(RLC!$C:$C,E1350)} -> 259.09008 | G1350: =C1350>E1350 -> FALSE
A1351: элементов | B1351: 92 | C1351: 29.532501 | D1351: =RANK(B1351,$B:$B,0) -> 1326 | E1351: =MATCH(A1351,RLC!$A:$A,0) -> 4112 | F1351: {=INDEX(RLC!$C:$C,E1351)} -> 27.902008
A1352: этими | B1352: 92 | C1352: 29.532501 | D1352: =RANK(B1352,$B:$B,0) -> 1326 | E1352: =MATCH(A1352,RLC!$A:$A,0) -> 1492 | F1352: {=INDEX(RLC!$C:$C,E1352)} -> 77.062689
A1353: артикля | B1353: 91 | C1353: 29.211495 | D1353: =RANK(B1353,$B:$B,0) -> 1352 | E1353: =MATCH(A1353,RLC!$A:$A,0) -> #N/A | F1353: {=INDEX(RLC!$C:$C,E1353)} -> #N/A
A1354: всему | B1354: 91 | C1354: 29.211495 | D1354: =RANK(B1354,$B:$B,0) -> 1352 | E1354: =MATCH(A1354,RLC!$A:$A,0) -> 741 | F1354: {=INDEX(RLC!$C:$C,E1354)} -> 144.82471
A1355: выполнения | B1355: 91 | C1355: 29.211495 | D1355: =RANK(B1355,$B:$B,0) -> 1352 | E1355: =MATCH(A1355,RLC!$A:$A,0) -> #N/A | F1355: {=INDEX(RLC!$C:$C,E1355)} -> #N/A
A1356: достоевский | B1356: 91 | C1356: 29.211495 | D1356: =RANK(B1356,$B:$B,0) -> 1352 | E1356: =MATCH(A1356,RLC!$A:$A,0) -> #N/A | F1356: {=INDEX(RLC!$C:$C,E1356)} -> #N/A
A1357: менеджмента | B1357: 91 | C1357: 29.211495 | D1357: =RANK(B1357,$B:$B,0) -> 1352 | E1357: =MATCH(A1357,RLC!$A:$A,0) -> 2858 | F1357: {=INDEX(RLC!$C:$C,E1357)} -> 39.860012
A1358: наша | B1358: 91 | C1358: 29.211495 | D1358: =RANK(B1358,$B:$B,0) -> 1352 | E1358: =MATCH(A1358,RLC!$A:$A,0) -> 551 | F1358: {=INDEX(RLC!$C:$C,E1358)} -> 193.98539
A1359: поднятая | B1359: 91 | C1359: 29.211495 | D1359: =RANK(B1359,$B:$B,0) -> 1352 | E1359: =MATCH(A1359,RLC!$A:$A,0) -> #N/A | F1359: {=INDEX(RLC!$C:$C,E1359)} -> #N/A
A1360: постепенно | B1360: 91 | C1360: 29.211495 | D1360: =RANK(B1360,$B:$B,0) -> 1352 | E1360: =MATCH(A1360,RLC!$A:$A,0) -> 2469 | F1360: {=INDEX(RLC!$C:$C,E1360)} -> 46.503347
A1361: рублей | B1361: 91 | C1361: 29.211495 | D1361: =RANK(B1361,$B:$B,0) -> 1352 | E1361: =MATCH(A1361,RLC!$A:$A,0) -> 1697 | F1361: {=INDEX(RLC!$C:$C,E1361)} -> 67.76202
A1362: сегодняшний | B1362: 91 | C1362: 29.211495 | D1362: =RANK(B1362,$B:$B,0) -> 1352 | E1362: =MATCH(A1362,RLC!$A:$A,0) -> 1873 | F1362: {=INDEX(RLC!$C:$C,E1362)} -> 62.447352
... A1716: чехов | B1716: 73 | C1716: 23.433397 | D1716: =RANK(B1716,$B:$B,0) -> 1684 | E1716: =MATCH(A1716,RLC!$A:$A,0) -> #N/A | F1716: {=INDEX(RLC!$C:$C,E1716)} -> #N/A
A1717: шапочка | B1717: 73 | C1717: 23.433397 | D1717: =RANK(B1717,$B:$B,0) -> 1684 | E1717: =MATCH(A1717,RLC!$A:$A,0) -> 3340 | F1717: {=INDEX(RLC!$C:$C,E1717)} -> 34.545343 | G1717: =C1717>E1717 -> FALSE
A1718: широко | B1718: 73 | C1718: 23.433397 | D1718: =RANK(B1718,$B:$B,0) -> 1684 | E1718: =MATCH(A1718,RLC!$A:$A,0) -> 1585 | F1718: {=INDEX(RLC!$C:$C,E1718)} -> 73.076688 | G1718: =C1718>E1718 -> FALSE
A1719: эмоций | B1719: 73 | C1719: 23.433397 | D1719: =RANK(B1719,$B:$B,0) -> 1684 | E1719: =MATCH(A1719,RLC!$A:$A,0) -> 6913 | F1719: {=INDEX(RLC!$C:$C,E1719)} -> 15.944005
A1720: большие | B1720: 72 | C1720: 23.112392 | D1720: =RANK(B1720,$B:$B,0) -> 1719 | E1720: =MATCH(A1720,RLC!$A:$A,0) -> 837 | F1720: {=INDEX(RLC!$C:$C,E1720)} -> 128.8807
A1721: большого | B1721: 72 | C1721: 23.112392 | D1721: =RANK(B1721,$B:$B,0) -> 1719 | E1721: =MATCH(A1721,RLC!$A:$A,0) -> 2651 | F1721: {=INDEX(RLC!$C:$C,E1721)} -> 42.517346
A1722: ведет | B1722: 72 | C1722: 23.112392 | D1722: =RANK(B1722,$B:$B,0) -> 1719 | E1722: =MATCH(A1722,RLC!$A:$A,0) -> 3483 | F1722: {=INDEX(RLC!$C:$C,E1722)} -> 31.888009
A1723: вниз | B1723: 72 | C1723: 23.112392 | D1723: =RANK(B1723,$B:$B,0) -> 1719 | E1723: =MATCH(A1723,RLC!$A:$A,0) -> 2832 | F1723: {=INDEX(RLC!$C:$C,E1723)} -> 39.860012
A1724: вузов | B1724: 72 | C1724: 23.112392 | D1724: =RANK(B1724,$B:$B,0) -> 1719 | E1724: =MATCH(A1724,RLC!$A:$A,0) -> 6052 | F1724: {=INDEX(RLC!$C:$C,E1724)} -> 17.272672
A1725: выражений | B1725: 72 | C1725: 23.112392 | D1725: =RANK(B1725,$B:$B,0) -> 1719 | E1725: =MATCH(A1725,RLC!$A:$A,0) -> 3786 | F1725: {=INDEX(RLC!$C:$C,E1725)} -> 29.230675
A1726: гражданским | B1726: 72 | C1726: 23.112392 | D1726: =RANK(B1726,$B:$B,0) -> 1719 | E1726: =MATCH(A1726,RLC!$A:$A,0) -> #N/A | F1726: {=INDEX(RLC!$C:$C,E1726)} -> #N/A
A1727: изучить | B1727: 72 | C1727: 23.112392 | D1727: =RANK(B1727,$B:$B,0) -> 1719 | E1727: =MATCH(A1727,RLC!$A:$A,0) -> 4372 | F1727: {=INDEX(RLC!$C:$C,E1727)} -> 25.244674
A1728: ин | B1728: 72 | C1728: 23.112392 | D1728: =RANK(B1728,$B:$B,0) -> 1719 | E1728: =MATCH(A1728,RLC!$A:$A,0) -> #N/A | F1728: {=INDEX(RLC!$C:$C,E1728)} -> #N/A
A1729: интернета | B1729: 72 | C1729: 23.112392 | D1729: =RANK(B1729,$B:$B,0) -> 1719 | E1729: =MATCH(A1729,RLC!$A:$A,0) -> 2960 | F1729: {=INDEX(RLC!$C:$C,E1729)} -> 38.531345
A1730: когнитивных | B1730: 72 | C1730: 23.112392 | D1730: =RANK(B1730,$B:$B,0) -> 1719 | E1730: =MATCH(A1730,RLC!$A:$A,0) -> #N/A | F1730: {=INDEX(RLC!$C:$C,E1730)} -> #N/A
... A2090: чтение | B2090: 61 | C2090: 19.581332 | D2090: =RANK(B2090,$B:$B,0) -> 2063 | E2090: =MATCH(A2090,RLC!$A:$A,0) -> 2647 | F2090: {=INDEX(RLC!$C:$C,E2090)} -> 43.846013
A2091: школы | B2091: 61 | C2091: 19.581332 | D2091: =RANK(B2091,$B:$B,0) -> 2063 | E2091: =MATCH(A2091,RLC!$A:$A,0) -> 542 | F2091: {=INDEX(RLC!$C:$C,E2091)} -> 197.97139 | G2091: =C2091>E2091 -> FALSE
A2092: больших | B2092: 60 | C2092: 19.260326 | D2092: =RANK(B2092,$B:$B,0) -> 2091 | E2092: =MATCH(A2092,RLC!$A:$A,0) -> 1082 | F2092: {=INDEX(RLC!$C:$C,E2092)} -> 102.30736
A2093: будем | B2093: 60 | C2093: 19.260326 | D2093: =RANK(B2093,$B:$B,0) -> 2091 | E2093: =MATCH(A2093,RLC!$A:$A,0) -> 1097 | F2093: {=INDEX(RLC!$C:$C,E2093)} -> 100.9787
A2094: вариативность | B2094: 60 | C2094: 19.260326 | D2094: =RANK(B2094,$B:$B,0) -> 2091 | E2094: =MATCH(A2094,RLC!$A:$A,0) -> #N/A | F2094: {=INDEX(RLC!$C:$C,E2094)} -> #N/A
A2095: возмещения | B2095: 60 | C2095: 19.260326 | D2095: =RANK(B2095,$B:$B,0) -> 2091 | E2095: =MATCH(A2095,RLC!$A:$A,0) -> #N/A | F2095: {=INDEX(RLC!$C:$C,E2095)} -> #N/A
A2096: возможностей | B2096: 60 | C2096: 19.260326 | D2096: =RANK(B2096,$B:$B,0) -> 2091 | E2096: =MATCH(A2096,RLC!$A:$A,0) -> 2835 | F2096: {=INDEX(RLC!$C:$C,E2096)} -> 39.860012
A2097: выяснить | B2097: 60 | C2097: 19.260326 | D2097: =RANK(B2097,$B:$B,0) -> 2091 | E2097: =MATCH(A2097,RLC!$A:$A,0) -> 7547 | F2097: {=INDEX(RLC!$C:$C,E2097)} -> 13.286671
A2098: гипотез | B2098: 60 | C2098: 19.260326 | D2098: =RANK(B2098,$B:$B,0) -> 2091 | E2098: =MATCH(A2098,RLC!$A:$A,0) -> #N/A | F2098: {=INDEX(RLC!$C:$C,E2098)} -> #N/A
A2099: голове | B2099: 60 | C2099: 19.260326 | D2099: =RANK(B2099,$B:$B,0) -> 2091 | E2099: =MATCH(A2099,RLC!$A:$A,0) -> 2131 | F2099: {=INDEX(RLC!$C:$C,E2099)} -> 53.146682
A2100: гражданском | B2100: 60 | C2100: 19.260326 | D2100: =RANK(B2100,$B:$B,0) -> 2091 | E2100: =MATCH(A2100,RLC!$A:$A,0) -> #N/A | F2100: {=INDEX(RLC!$C:$C,E2100)} -> #N/A
A2101: дается | B2101: 60 | C2101: 19.260326 | D2101: =RANK(B2101,$B:$B,0) -> 2091 | E2101: =MATCH(A2101,RLC!$A:$A,0) -> 4145 | F2101: {=INDEX(RLC!$C:$C,E2101)} -> 26.573341
A2102: дальнейшего | B2102: 60 | C2102: 19.260326 | D2102: =RANK(B2102,$B:$B,0) -> 2091 | E2102: =MATCH(A2102,RLC!$A:$A,0) -> #N/A | F2102: {=INDEX(RLC!$C:$C,E2102)} -> #N/A
A2103: другая | B2103: 60 | C2103: 19.260326 | D2103: =RANK(B2103,$B:$B,0) -> 2091 | E2103: =MATCH(A2103,RLC!$A:$A,0) -> 1157 | F2103: {=INDEX(RLC!$C:$C,E2103)} -> 96.992695
... A2510: фоне | B2510: 50 | C2510: 16.050272 | D2510: =RANK(B2510,$B:$B,0) -> 2456 | E2510: =MATCH(A2510,RLC!$A:$A,0) -> #N/A | F2510: {=INDEX(RLC!$C:$C,E2510)} -> #N/A
A2511: широкий | B2511: 50 | C2511: 16.050272 | D2511: =RANK(B2511,$B:$B,0) -> 2456 | E2511: =MATCH(A2511,RLC!$A:$A,0) -> 6907 | F2511: {=INDEX(RLC!$C:$C,E2511)} -> 15.944005 | G2511: =C2511>E2511 -> FALSE
A2512: адресован | B2512: 49 | C2512: 15.729267 | D2512: =RANK(B2512,$B:$B,0) -> 2511 | E2512: =MATCH(A2512,RLC!$A:$A,0) -> #N/A | F2512: {=INDEX(RLC!$C:$C,E2512)} -> #N/A
A2513: база | B2513: 49 | C2513: 15.729267 | D2513: =RANK(B2513,$B:$B,0) -> 2511 | E2513: =MATCH(A2513,RLC!$A:$A,0) -> #N/A | F2513: {=INDEX(RLC!$C:$C,E2513)} -> #N/A
A2514: вариативности | B2514: 49 | C2514: 15.729267 | D2514: =RANK(B2514,$B:$B,0) -> 2511 | E2514: =MATCH(A2514,RLC!$A:$A,0) -> #N/A | F2514: {=INDEX(RLC!$C:$C,E2514)} -> #N/A
A2515: введения | B2515: 49 | C2515: 15.729267 | D2515: =RANK(B2515,$B:$B,0) -> 2511 | E2515: =MATCH(A2515,RLC!$A:$A,0) -> 7509 | F2515: {=INDEX(RLC!$C:$C,E2515)} -> 13.286671
A2516: видел | B2516: 49 | C2516: 15.729267 | D2516: =RANK(B2516,$B:$B,0) -> 2511 | E2516: =MATCH(A2516,RLC!$A:$A,0) -> 1926 | F2516: {=INDEX(RLC!$C:$C,E2516)} -> 59.790017
A2517: высокий | B2517: 49 | C2517: 15.729267 | D2517: =RANK(B2517,$B:$B,0) -> 2511 | E2517: =MATCH(A2517,RLC!$A:$A,0) -> 2129 | F2517: {=INDEX(RLC!$C:$C,E2517)} -> 53.146682
A2518: выходит | B2518: 49 | C2518: 15.729267 | D2518: =RANK(B2518,$B:$B,0) -> 2511 | E2518: =MATCH(A2518,RLC!$A:$A,0) -> 3637 | F2518: {=INDEX(RLC!$C:$C,E2518)} -> 30.559342
A2519: герои | B2519: 49 | C2519: 15.729267 | D2519: =RANK(B2519,$B:$B,0) -> 2511 | E2519: =MATCH(A2519,RLC!$A:$A,0) -> 2502 | F2519: {=INDEX(RLC!$C:$C,E2519)} -> 45.17468
A2520: глагольных | B2520: 49 | C2520: 15.729267 | D2520: =RANK(B2520,$B:$B,0) -> 2511 | E2520: =MATCH(A2520,RLC!$A:$A,0) -> #N/A | F2520: {=INDEX(RLC!$C:$C,E2520)} -> #N/A
A2521: гпк | B2521: 49 | C2521: 15.729267 | D2521: =RANK(B2521,$B:$B,0) -> 2511 | E2521: =MATCH(A2521,RLC!$A:$A,0) -> #N/A | F2521: {=INDEX(RLC!$C:$C,E2521)} -> #N/A
A2522: егэ | B2522: 49 | C2522: 15.729267 | D2522: =RANK(B2522,$B:$B,0) -> 2511 | E2522: =MATCH(A2522,RLC!$A:$A,0) -> 3049 | F2522: {=INDEX(RLC!$C:$C,E2522)} -> 37.202678
A2523: единственный | B2523: 49 | C2523: 15.729267 | D2523: =RANK(B2523,$B:$B,0) -> 2511 | E2523: =MATCH(A2523,RLC!$A:$A,0) -> 1892 | F2523: {=INDEX(RLC!$C:$C,E2523)} -> 61.118685
... A2664: человеке | B2664: 47 | C2664: 15.087256 | D2664: =RANK(B2664,$B:$B,0) -> 2608 | E2664: =MATCH(A2664,RLC!$A:$A,0) -> 2556 | F2664: {=INDEX(RLC!$C:$C,E2664)} -> 45.17468
A2665: шаг | B2665: 47 | C2665: 15.087256 | D2665: =RANK(B2665,$B:$B,0) -> 2608 | E2665: =MATCH(A2665,RLC!$A:$A,0) -> 2738 | F2665: {=INDEX(RLC!$C:$C,E2665)} -> 42.517346 | G2665: =C2665>E2665 -> FALSE
A2666: авторских | B2666: 46 | C2666: 14.76625 | D2666: =RANK(B2666,$B:$B,0) -> 2665 | E2666: =MATCH(A2666,RLC!$A:$A,0) -> #N/A | F2666: {=INDEX(RLC!$C:$C,E2666)} -> #N/A
A2667: будь | B2667: 46 | C2667: 14.76625 | D2667: =RANK(B2667,$B:$B,0) -> 2665 | E2667: =MATCH(A2667,RLC!$A:$A,0) -> 3245 | F2667: {=INDEX(RLC!$C:$C,E2667)} -> 34.545343
A2668: бытия | B2668: 46 | C2668: 14.76625 | D2668: =RANK(B2668,$B:$B,0) -> 2665 | E2668: =MATCH(A2668,RLC!$A:$A,0) -> #N/A | F2668: {=INDEX(RLC!$C:$C,E2668)} -> #N/A
A2669: вводит | B2669: 46 | C2669: 14.76625 | D2669: =RANK(B2669,$B:$B,0) -> 2665 | E2669: =MATCH(A2669,RLC!$A:$A,0) -> #N/A | F2669: {=INDEX(RLC!$C:$C,E2669)} -> #N/A
A2670: вещь | B2670: 46 | C2670: 14.76625 | D2670: =RANK(B2670,$B:$B,0) -> 2665 | E2670: =MATCH(A2670,RLC!$A:$A,0) -> 2655 | F2670: {=INDEX(RLC!$C:$C,E2670)} -> 42.517346
A2671: взаимодействии | B2671: 46 | C2671: 14.76625 | D2671: =RANK(B2671,$B:$B,0) -> 2665 | E2671: =MATCH(A2671,RLC!$A:$A,0) -> #N/A | F2671: {=INDEX(RLC!$C:$C,E2671)} -> #N/A
A2672: выборки | B2672: 46 | C2672: 14.76625 | D2672: =RANK(B2672,$B:$B,0) -> 2665 | E2672: =MATCH(A2672,RLC!$A:$A,0) -> #N/A | F2672: {=INDEX(RLC!$C:$C,E2672)} -> #N/A
A2673: выделены | B2673: 46 | C2673: 14.76625 | D2673: =RANK(B2673,$B:$B,0) -> 2665 | E2673: =MATCH(A2673,RLC!$A:$A,0) -> #N/A | F2673: {=INDEX(RLC!$C:$C,E2673)} -> #N/A
A2674: гипотезу | B2674: 46 | C2674: 14.76625 | D2674: =RANK(B2674,$B:$B,0) -> 2665 | E2674: =MATCH(A2674,RLC!$A:$A,0) -> #N/A | F2674: {=INDEX(RLC!$C:$C,E2674)} -> #N/A
A2675: государств | B2675: 46 | C2675: 14.76625 | D2675: =RANK(B2675,$B:$B,0) -> 2665 | E2675: =MATCH(A2675,RLC!$A:$A,0) -> 991 | F2675: {=INDEX(RLC!$C:$C,E2675)} -> 111.60803
A2676: доме | B2676: 46 | C2676: 14.76625 | D2676: =RANK(B2676,$B:$B,0) -> 2665 | E2676: =MATCH(A2676,RLC!$A:$A,0) -> 907 | F2676: {=INDEX(RLC!$C:$C,E2676)} -> 120.9087
A2677: думать | B2677: 46 | C2677: 14.76625 | D2677: =RANK(B2677,$B:$B,0) -> 2665 | E2677: =MATCH(A2677,RLC!$A:$A,0) -> 720 | F2677: {=INDEX(RLC!$C:$C,E2677)} -> 147.48204
... A2830: ценностей | B2830: 44 | C2830: 14.124239 | D2830: =RANK(B2830,$B:$B,0) -> 2779 | E2830: =MATCH(A2830,RLC!$A:$A,0) -> 1925 | F2830: {=INDEX(RLC!$C:$C,E2830)} -> 61.118685
A2831: широкого | B2831: 44 | C2831: 14.124239 | D2831: =RANK(B2831,$B:$B,0) -> 2779 | E2831: =MATCH(A2831,RLC!$A:$A,0) -> 5302 | F2831: {=INDEX(RLC!$C:$C,E2831)} -> 21.258673 | G2831: =C2831>E2831 -> FALSE
A2832: широкой | B2832: 44 | C2832: 14.124239 | D2832: =RANK(B2832,$B:$B,0) -> 2779 | E2832: =MATCH(A2832,RLC!$A:$A,0) -> 1998 | F2832: {=INDEX(RLC!$C:$C,E2832)} -> 58.46135 | G2832: =C2832>E2832 -> FALSE
A2833: экономиста | B2833: 44 | C2833: 14.124239 | D2833: =RANK(B2833,$B:$B,0) -> 2779 | E2833: =MATCH(A2833,RLC!$A:$A,0) -> #N/A | F2833: {=INDEX(RLC!$C:$C,E2833)} -> #N/A
A2834: экономического | B2834: 44 | C2834: 14.124239 | D2834: =RANK(B2834,$B:$B,0) -> 2779 | E2834: =MATCH(A2834,RLC!$A:$A,0) -> 917 | F2834: {=INDEX(RLC!$C:$C,E2834)} -> 120.9087
A2835: эксперта | B2835: 44 | C2835: 14.124239 | D2835: =RANK(B2835,$B:$B,0) -> 2779 | E2835: =MATCH(A2835,RLC!$A:$A,0) -> #N/A | F2835: {=INDEX(RLC!$C:$C,E2835)} -> #N/A
A2836: января | B2836: 44 | C2836: 14.124239 | D2836: =RANK(B2836,$B:$B,0) -> 2779 | E2836: =MATCH(A2836,RLC!$A:$A,0) -> 1413 | F2836: {=INDEX(RLC!$C:$C,E2836)} -> 81.04869
A2837: абстрактное | B2837: 43 | C2837: 13.803234 | D2837: =RANK(B2837,$B:$B,0) -> 2836 | E2837: =MATCH(A2837,RLC!$A:$A,0) -> #N/A | F2837: {=INDEX(RLC!$C:$C,E2837)} -> #N/A
A2838: автору | B2838: 43 | C2838: 13.803234 | D2838: =RANK(B2838,$B:$B,0) -> 2836 | E2838: =MATCH(A2838,RLC!$A:$A,0) -> 6004 | F2838: {=INDEX(RLC!$C:$C,E2838)} -> 17.272672
A2839: включая | B2839: 43 | C2839: 13.803234 | D2839: =RANK(B2839,$B:$B,0) -> 2836 | E2839: =MATCH(A2839,RLC!$A:$A,0) -> 1415 | F2839: {=INDEX(RLC!$C:$C,E2839)} -> 79.720023
A2840: встретить | B2840: 43 | C2840: 13.803234 | D2840: =RANK(B2840,$B:$B,0) -> 2836 | E2840: =MATCH(A2840,RLC!$A:$A,0) -> 4555 | F2840: {=INDEX(RLC!$C:$C,E2840)} -> 23.916007
A2841: выяснилось | B2841: 43 | C2841: 13.803234 | D2841: =RANK(B2841,$B:$B,0) -> 2836 | E2841: =MATCH(A2841,RLC!$A:$A,0) -> 6485 | F2841: {=INDEX(RLC!$C:$C,E2841)} -> 15.944005
A2842: грамматика | B2842: 43 | C2842: 13.803234 | D2842: =RANK(B2842,$B:$B,0) -> 2836 | E2842: =MATCH(A2842,RLC!$A:$A,0) -> 6065 | F2842: {=INDEX(RLC!$C:$C,E2842)} -> 17.272672
A2843: движений | B2843: 43 | C2843: 13.803234 | D2843: =RANK(B2843,$B:$B,0) -> 2836 | E2843: =MATCH(A2843,RLC!$A:$A,0) -> 4347 | F2843: {=INDEX(RLC!$C:$C,E2843)} -> 25.244674
A2844: доказывает | B2844: 43 | C2844: 13.803234 | D2844: =RANK(B2844,$B:$B,0) -> 2836 | E2844: =MATCH(A2844,RLC!$A:$A,0) -> 2364 | F2844: {=INDEX(RLC!$C:$C,E2844)} -> 47.832014
... A3829: чувством | B3829: 32 | C3829: 10.272174 | D3829: =RANK(B3829,$B:$B,0) -> 3719 | E3829: =MATCH(A3829,RLC!$A:$A,0) -> 6906 | F3829: {=INDEX(RLC!$C:$C,E3829)} -> 15.944005
...

Sheet RLC
A1: Слово | B1: Частота-RLC | C1: IPM-RLC | D1: Ранг-RLC | E1: Номер строки, на которой слово стоит в CorST
A2: и | B2: 28852 | C2: 38334.702 | D2: =RANK(B2,$B:$B,0) -> 1 | E2: =MATCH(A2,CorST!$A:$A,0) -> 3
A3: в | B3: 28595 | C3: 37993.234 | D3: =RANK(B3,$B:$B,0) -> 2 | E3: =MATCH(A3,CorST!$A:$A,0) -> 2
A4: что | B4: 12272 | C4: 16305.402 | D4: =RANK(B4,$B:$B,0) -> 3 | E4: =MATCH(A4,CorST!$A:$A,0) -> 7
A5: на | B5: 9984 | C5: 13265.412 | D5: =RANK(B5,$B:$B,0) -> 4 | E5: =MATCH(A5,CorST!$A:$A,0) -> 4
A6: не | B6: 9679 | C6: 12860.168 | D6: =RANK(B6,$B:$B,0) -> 5 | E6: =MATCH(A6,CorST!$A:$A,0) -> 5
A7: я | B7: 8489 | C7: 11279.055 | D7: =RANK(B7,$B:$B,0) -> 6 | E7: =MATCH(A7,CorST!$A:$A,0) -> 24
A8: с | B8: 6908 | C8: 9178.432 | D8: =RANK(B8,$B:$B,0) -> 7 | E8: =MATCH(A8,CorST!$A:$A,0) -> 6
A9: как | B9: 6227 | C9: 8273.6097 | D9: =RANK(B9,$B:$B,0) -> 8 | E9: =MATCH(A9,CorST!$A:$A,0) -> 8
A10: это | B10: 5389 | C10: 7160.1868 | D10: =RANK(B10,$B:$B,0) -> 9 | E10: =MATCH(A10,CorST!$A:$A,0) -> 15
A11: но | B11: 4307 | C11: 5722.569 | D11: =RANK(B11,$B:$B,0) -> 10 | E11: =MATCH(A11,CorST!$A:$A,0) -> 19
A12: он | B12: 4050 | C12: 5381.1016 | D12: =RANK(B12,$B:$B,0) -> 11 | E12: =MATCH(A12,CorST!$A:$A,0) -> 21
A13: о | B13: 3780 | C13: 5022.3615 | D13: =RANK(B13,$B:$B,0) -> 12 | E13: =MATCH(A13,CorST!$A:$A,0) -> 13
... A8127: японский | B8127: 10 | C8127: 13.286671 | D8127: =RANK(B8127,$B:$B,0) -> 7471 | E8127: =MATCH(A8127,CorST!$A:$A,0) -> 14067

Sheet merge
A1: Слово | B1: IPM-CorST | C1: IPM-RLC
A2: а | B2: 1901.6362 | C2: 3449.2197
A3: аббревиатуры | B3: 4.4940762
A4: абзац | B4: 86.029458 | C4: 75.734022
A5: абзаца | B5: 51.039865
A6: абзаце | B6: 43.014729 | C6: 23.916007
A7: абзацев | B7: 12.198207
A8: абзацу | B8: 3.5310598
A9: абзацы | B9: 43.65674
A10: абитуриентов | B10: 3.2100544 | C10: 27.902008
A11: абитуриенты | C11: 15.944005
A12: абрамова | B12: 3.2100544
A13: абсолютно | B13: 35.631604 | C13: 81.04869
A14: абсолютной | B14: 4.1730707
A15: абстрагироваться | B15: 5.4570925
A16: абстрактного | B16: 6.7411142
A17: абстрактное | B17: 13.803234
A18: абстрактном | B18: 3.5310598
A19: абстрактные | B19: 8.6671469 | C19: 14.615338
A20: абстрактный | B20: 4.1730707
A21: абстрактным | B21: 6.0991034
A22: абстрактными | B22: 3.2100544
A23: абстрактных | B23: 5.4570925
A24: абсурд | B24: 3.2100544
A25: абсурда | B25: 9.3091578 | C25: 13.286671
A26: авангард | C26: 14.615338
A27: авангарда | C27: 43.846013
A28: авангардистов | C28: 15.944005
A29: авангардные | C29: 15.944005
A30: аварии | C30: 38.531345
A31: авария | C31: 14.615338
A32: август | B32: 18.29731
A33: августа | B33: 25.680435 | C33: 57.132683
A34: августе | C34: 13.286671
A35: австрийский | B35: 6.4201088
A36: австрийского | B36: 5.4570925
A37: автобиографическое | B37: 4.8150816
A38: автобиография | B38: 3.2100544
A39: автобус | B39: 3.8520653 | C39: 14.615338
A40: автобусе | C40: 17.272672
A41: автолюбителей | B41: 5.4570925
A42: автоматизмов | B42: 3.8520653
A43: автоматизмы | B43: 5.136087
A44: автоматически | B44: 6.0991034
A45: автомобилей | B45: 8.3461415
A46: автомобилистов | B46: 4.8150816
A47: автомобиль | B47: 17.976305
A48: автомобильная | B48: 15.408261
A49: автомобильной | B49: 7.7041306
A50: автомобильных | B50: 3.8520653
A51: автомобиля | B51: 4.1730707
A52: автоперевозки | B52: 3.2100544
A53: автор | B53: 503.65754 | C53: 964.61228
A54: автора | B54: 112.99392 | C54: 223.21607
A55: авторам | B55: 5.4570925
A56: авторами | B56: 14.445245
A57: авторитет | B57: 17.334294 | C57: 23.916007
A58: авторитетом | B58: 5.136087
A59: авторов | B59: 35.952609 | C59: 37.202678
A60: автором | B60: 94.375599 | C60: 46.503347
A61: авторская | B61: 7.0621197
A62: авторские | B62: 3.2100544
A63: авторских | B63: 14.76625
A64: авторского | B64: 14.124239
A65: авторское | B65: 7.3831251
A66: авторской | B66: 16.692283
A67: авторском | B67: 3.5310598
A68: авторства | B68: 3.2100544
A69: авторство | B69: 3.8520653
A70: автору | B70: 13.803234 | C70: 17.272672
A71: авторы | B71: 77.683317 | C71: 111.60803
A72: автошколах | B72: 3.5310598
A73: агенство | C73: 15.944005
A74: агентства | B74: 3.8520653
A75: агентство | B75: 3.5310598
A76: ад | B76: 4.8150816
A77: ада | B77: 4.8150816
A78: адаптации | B78: 16.371277 | C78: 26.573341
A79: адаптацию | B79: 3.5310598
A80: адаптация | B80: 6.4201088 | C80: 14.615338
A81: адаптироваться | C81: 37.202678
A82: адвербиальный | B82: 4.4940762
A83: адвокат | B83: 7.7041306
A84: адвоката | B84: 5.7780979
A85: адвокатов | B85: 3.5310598
A86: адвокаты | B86: 4.1730707
A87: адекватно | B87: 5.136087
A88: адекватного | B88: 4.8150816
A89: административная | B89: 3.2100544
A90: административного | B90: 12.519212
A91: административное | B91: 6.0991034
A92: административной | B92: 5.4570925
A93: административно-правовые | B93: 6.4201088
... A96: административных | B96: 9.9511687
A97: администрации | B97: 4.8150816 | C97: 13.286671
A98: адрес | B98: 8.9881523
A99: адресантом | B99: 3.2100544
A100: адресат | B100: 10.272174
A101: адресата | B101: 9.9511687
A102: адресатом | B102: 9.6301632
...
